pyrof/__init__.py
pyrof/common.py
pyrof/menu.py
pyrof/rofi.py
pyrof/cmd/__init__.py
pyrof/cmd/async.py
pyrof/cmd/async_py3.py
pyrof/cmd/blocking.py
pyrof/cmd/futures.py
pyrof-0.1.1.dist-info/LICENSE
pyrof-0.1.1.dist-info/METADATA
pyrof-0.1.1.dist-info/WHEEL
pyrof-0.1.1.dist-info/top_level.txt
pyrof-0.1.1.dist-info/RECORD
