Metadata-Version: 2.1
Name: pyrof
Version: 0.1.1
Summary: Python wrappers for dynamic menus (rofi, fzf)
Home-page: https://gitlab.com/nesstero/pyrof
Maintainer: nestero
Maintainer-email: nestero@mail.com
License: MIT
Platform: UNKNOWN
License-File: LICENSE
Requires-Dist: traitlets
